czitools/__init__.py
czitools/metadata_tools/__init__.py
czitools/metadata_tools/add_metadata.py
czitools/metadata_tools/attachment.py
czitools/metadata_tools/boundingbox.py
czitools/metadata_tools/channel.py
czitools/metadata_tools/czi_metadata.py
czitools/metadata_tools/detector.py
czitools/metadata_tools/dimension.py
czitools/metadata_tools/helper.py
czitools/metadata_tools/microscope.py
czitools/metadata_tools/objective.py
czitools/metadata_tools/sample.py
czitools/metadata_tools/scaling.py
czitools/metadata_tools/scene.py
czitools/read_tools/__init__.py
czitools/read_tools/read_tools.py
czitools/utils/__init__.py
czitools/utils/box.py
czitools/utils/logging_tools.py
czitools/utils/misc.py
czitools/utils/napari_helpers.py
czitools/utils/napari_tools.py
czitools/utils/pixels.py
czitools/utils/planetable.py
czitools/utils/threading_helpers.py
czitools/visu_tools/__init__.py
czitools/visu_tools/vis_tools.py
czitools-0.13.2.dist-info/licenses/LICENSE
czitools-0.13.2.dist-info/METADATA
czitools-0.13.2.dist-info/WHEEL
czitools-0.13.2.dist-info/top_level.txt
czitools-0.13.2.dist-info/RECORD
