Metadata-Version: 2.4
Name: czitools
Version: 0.13.2
Summary: Tools to simplify reading and CZI (Carl Zeiss Image) meta and pixel data
Home-page: https://github.com/sebi06/czitools
Author: Sebastian Rhode
Author-email: sebrhode@gmail.com
License: GNU General Public License v3 (GPLv3)
Project-URL: Bug Tracker, https://github.com/sebi06/czitools/issues
Project-URL: Documentation, https://github.com/sebi06/czitools/#README.md
Project-URL: Source Code, https://github.com/sebi06/czitools/
Project-URL: User Support, https://github.com/sebi06/czitools//issues
Classifier: Development Status :: 4 - Beta
Classifier: Intended Audience :: Science/Research
Classifier: Intended Audience :: Developers
Classifier: Topic :: Scientific/Engineering
Classifier: Programming Language :: Python
Classifier: Programming Language :: Python :: 3
Classifier: Programming Language :: Python :: 3.10
Classifier: Programming Language :: Python :: 3.11
Classifier: Programming Language :: Python :: 3.12
Classifier: Programming Language :: Python :: 3.13
Classifier: Operating System :: Unix
Classifier: Operating System :: Microsoft :: Windows
Requires-Python: <3.14,>=3.10
License-File: LICENSE
Requires-Dist: pylibCZIrw>=5
Requires-Dist: aicspylibczi>=3.3.1
Requires-Dist: progressbar2
Requires-Dist: pandas
Requires-Dist: python-dateutil
Requires-Dist: python-box[all]
Requires-Dist: czifile
Requires-Dist: loguru
Requires-Dist: colorlog
Requires-Dist: pydantic
Requires-Dist: xarray
Requires-Dist: xarray[complete]
Provides-Extra: all
Requires-Dist: seaborn; extra == "all"
Requires-Dist: plotly; extra == "all"
Requires-Dist: qtpy; extra == "all"
Requires-Dist: pyqtgraph; extra == "all"
Requires-Dist: colormap; extra == "all"
Requires-Dist: ngff-zarr; extra == "all"
Requires-Dist: ngff-zarr[validate]; extra == "all"
Requires-Dist: ngff-zarr[dask-image]; extra == "all"
Requires-Dist: bioio; extra == "all"
Requires-Dist: bioio-czi; extra == "all"
Requires-Dist: bioio-ome-zarr; extra == "all"
Dynamic: license-file
